bishnu/__init__.py
bishnu/resume.py
bishnu_resume-1.0.0.dist-info/LICENSE
bishnu_resume-1.0.0.dist-info/METADATA
bishnu_resume-1.0.0.dist-info/WHEEL
bishnu_resume-1.0.0.dist-info/top_level.txt
bishnu_resume-1.0.0.dist-info/RECORD
