Metadata-Version: 2.1
Name: bishnu-resume
Version: 1.0.0
Summary: Python package containing Bishnu Prasad Sahu's complete resume and projects.
Home-page: https://github.com/mebishnusahu0595
Author: Bishnu Sahu
Author-email: Bishnu Prasad Sahu <mebishnusahu0595@gmail.com>
License: MIT
Classifier: Programming Language :: Python :: 3
Classifier: License :: OSI Approved :: MIT License
Classifier: Operating System :: OS Independent
Requires-Python: >=3.8
License-File: LICENSE
